README.rst
setup.py
typesafety/__init__.py
typesafety/autodecorator.py
typesafety/finder.py
typesafety/noseplugin.py
typesafety/pytest_typesafety.py
typesafety/sphinxautodoc.py
typesafety/typing_inspect.py
typesafety/validator.py
typesafety.egg-info/PKG-INFO
typesafety.egg-info/SOURCES.txt
typesafety.egg-info/dependency_links.txt
typesafety.egg-info/entry_points.txt
typesafety.egg-info/requires.txt
typesafety.egg-info/top_level.txt
typesafety.egg-info/zip-safe