Metadata-Version: 1.1
Name: typesafety
Version: 2.1.2
Summary: Type safety checker for Python3
Home-page: https://github.com/balabit/typesafety
Author: Viktor Hercinger
Author-email: viktor.hercinger@balabit.com
License: LGPLv2+
Keywords: nose type typesafe static
Platform: UNKNOWN
Classifier: Development Status :: 5 - Production/Stable
Classifier: Environment :: Console
Classifier: Intended Audience :: Developers
Classifier: License :: OSI Approved :: GNU Lesser General Public License v2 or later (LGPLv2+)
Classifier: Natural Language :: English
Classifier: Operating System :: OS Independent
Classifier: Programming Language :: Python
Classifier: Programming Language :: Python :: 3
Classifier: Programming Language :: Python :: 3.4
Classifier: Programming Language :: Python :: 3.5
Classifier: Programming Language :: Python :: 3.6
Classifier: Topic :: Software Development
Classifier: Topic :: Software Development :: Testing
Classifier: Topic :: Documentation :: Sphinx
